{
    "file": "wire\/modules\/Process\/ProcessRole\/ProcessRole.module",
    "textdomain": "wire--modules--process--processrole--processrole-module",
    "translations": {
        "a5cd3ed116608dac017f14c046ea56bf": {
            "text": "Roller"
        },
        "e5e77ccf470959bc6be60127730908b5": {
            "text": "Kullan\u0131c\u0131 rollerini ve rollere ekli izinleri y\u00f6net"
        },
        "d08ccf52b4cdd08e41cfb99ec42e0b29": {
            "text": "\u0130zinler"
        },
        "2ac1fce951ddece70a50dfb03bd386b2": {
            "text": "isim|baslik"
        },
        "9bfb6e6af6e6793bfa9387e728187c87": {
            "text": "(zorunlu)"
        },
        "abf1be1c76c0620d1a220871b1ba0da1": {
            "text": "Daha fazla izin se\u00e7eneklerini g\u00f6r\u00fcnt\u00fcleyebilmek i\u00e7in kutucu\u011fu i\u015faretleyip sayfay\u0131 kaydedin."
        },
        "55713ee9cd76b3704908899aaa30b5e5": {
            "text": "*Not burada sayfa-duzenleme (page-edit) iznini i\u015faretleyerek bu role sadece bu \u015fablon seviyesini d\u00fczenleme eri\u015fimini sa\u011flayacaks\u0131n\u0131z. Basit\u00e7e burada sayfa-duzenleme (page-edit) izni ataman\u0131z, di\u011fer \u015fablonlarda sayfa-d\u00fczenleme (page-edit) izni oldu\u011fu anlam\u0131na gelmez. Di\u011fer \u015fablonlara bu izni eklemedi\u011finiz taktirde bu sayfalar\u0131 d\u00fczenleme izni olmayacakt\u0131r."
        }
    }
}